zwpdf/__init__.py
zwpdf/__version__.py
zwpdf/pdf.py
zwpdf-0.0.3.dist-info/LICENSE
zwpdf-0.0.3.dist-info/METADATA
zwpdf-0.0.3.dist-info/WHEEL
zwpdf-0.0.3.dist-info/top_level.txt
zwpdf-0.0.3.dist-info/RECORD
